librarian/__init__.py
librarian/actor.py
librarian/catalog.py
librarian/librarian.py
librarian/actors/__init__.py
librarian/actors/plotter.py
librarian/actors/reader.py
librarian/actors/writer.py
librarian/plotters/__init__.py
librarian/plotters/errorbarplotter.py
librarian/plotters/histplotter.py
LibrarianFileManager-0.0.1.dist-info/LICENSE
LibrarianFileManager-0.0.1.dist-info/METADATA
LibrarianFileManager-0.0.1.dist-info/WHEEL
LibrarianFileManager-0.0.1.dist-info/top_level.txt
LibrarianFileManager-0.0.1.dist-info/RECORD
